__tests__
quoters
