Metadata-Version: 2.1
Name: quoters
Version: 0.30
Summary: Pythonic random quote generator
Home-page: https://github.com/suman-kr/quoters
Author: Suman Kumar
Author-email: skcool.123bgp@gmail.com
License: MIT
Download-URL: https://github.com/suman-kr/quoters/archive/0.30.tar.gz
Keywords: RANDOM,QUOTES,SCRAPPER
Platform: UNKNOWN
Classifier: Development Status :: 3 - Alpha
Classifier: Intended Audience :: Developers
Classifier: Topic :: Software Development :: Build Tools
Classifier: License :: OSI Approved :: MIT License
Classifier: Programming Language :: Python :: 3
Classifier: Programming Language :: Python :: 3.5
Classifier: Programming Language :: Python :: 3.6
Classifier: Programming Language :: Python :: 3.7
Classifier: Programming Language :: Python :: 3.8
